maximus/__init__.py
maximus/client.py
maximus/connection.py
maximus/database.py
maximus/events.py
maximus/session.py
maximus/storage.py
maximus/types.py
maximus/utils.py
maximus_client-0.1.2.dist-info/LICENSE
maximus_client-0.1.2.dist-info/METADATA
maximus_client-0.1.2.dist-info/WHEEL
maximus_client-0.1.2.dist-info/top_level.txt
maximus_client-0.1.2.dist-info/RECORD
