Metadata-Version: 2.2
Name: maximus-client
Version: 0.1.2
Summary: Python library for working with MAX messenger API through WebSocket connections
Author-email: Vodeninja <root@vodeninja.ru>
Project-URL: Homepage, https://github.com/Vodeninja/maximus-client
Project-URL: Bug Reports, https://github.com/Vodeninja/maximus-client/issues
Project-URL: Source Code, https://github.com/Vodeninja/maximus-client
Keywords: max,messenger,api,websocket,client
Classifier: Development Status :: 3 - Alpha
Classifier: Intended Audience :: Developers
Classifier: License :: OSI Approved :: MIT License
Classifier: Operating System :: OS Independent
Classifier: Programming Language :: Python :: 3
Classifier: Programming Language :: Python :: 3.8
Classifier: Programming Language :: Python :: 3.9
Classifier: Programming Language :: Python :: 3.10
Classifier: Programming Language :: Python :: 3.11
Classifier: Programming Language :: Python :: 3.12
Requires-Python: >=3.8
License-File: LICENSE
Requires-Dist: websockets>=12.0
Requires-Dist: sqlalchemy>=2.0.0
